README.md
setup.cfg
setup.py
funniest_kr/__init__.py
funniest_kr.egg-info/PKG-INFO
funniest_kr.egg-info/SOURCES.txt
funniest_kr.egg-info/dependency_links.txt
funniest_kr.egg-info/not-zip-safe
funniest_kr.egg-info/top_level.txt