Metadata-Version: 1.0
Name: funniest-kr
Version: 0.0.2
Summary: The AaZae gag for koreans
Home-page: https://github.com/bboyseiok/funniest_kr
Author: bboyseiok
Author-email: bboyseiok@deepest.ai
License: BSP
Platform: UNKNOWN
